{
	"background": "#232530",
	"black": "#06060C",
	"blue": "#26BBD9",
	"brightBlack": "#06060C",
	"brightBlue": "#3FC6DE",
	"brightCyan": "#6BE6E6",
	"brightGreen": "#3FDAA4",
	"brightPurple": "#F075B7",
	"brightRed": "#EC6A88",
	"brightWhite": "#D5D8DA",
	"brightYellow": "#FBC3A7",
	"cursorColor": "#D5D8DA",
	"cyan": "#59E3E3",
	"foreground": "#D5D8DA",
	"green": "#29D398",
	"name": "Horizon",
	"purple": "#EE64AE",
	"red": "#E95678",
	"selectionBackground": "#6C6F93",
	"white": "#D5D8DA",
	"yellow": "#FAB795"
}
